odoo10_addon_purchase_fiscal_position_update-10.0.1.0.0-py2.7-nspkg.pth
odoo10_addon_purchase_fiscal_position_update-10.0.1.0.0.dist-info/top_level.txt
odoo10_addon_purchase_fiscal_position_update-10.0.1.0.0.dist-info/WHEEL
odoo10_addon_purchase_fiscal_position_update-10.0.1.0.0.dist-info/RECORD
odoo10_addon_purchase_fiscal_position_update-10.0.1.0.0.dist-info/metadata.json
odoo10_addon_purchase_fiscal_position_update-10.0.1.0.0.dist-info/DESCRIPTION.rst
odoo10_addon_purchase_fiscal_position_update-10.0.1.0.0.dist-info/METADATA
odoo10_addon_purchase_fiscal_position_update-10.0.1.0.0.dist-info/namespace_packages.txt
odoo/addons/purchase_fiscal_position_update/__manifest__.py
odoo/addons/purchase_fiscal_position_update/__init__.py
odoo/addons/purchase_fiscal_position_update/README.rst
odoo/addons/purchase_fiscal_position_update/models/purchase.py
odoo/addons/purchase_fiscal_position_update/models/__init__.py
odoo/addons/purchase_fiscal_position_update/i18n/purchase_fiscal_position_update.pot
odoo/addons/purchase_fiscal_position_update/i18n/fr.po
odoo/addons/purchase_fiscal_position_update/static/description/icon.png
