Metadata-Version: 2.0
Name: odoo10-addon-purchase-fiscal-position-update
Version: 10.0.1.0.0
Summary: Changing the fiscal position of a purchase order will auto-update purchase order lines
Home-page: UNKNOWN
Author: UNKNOWN
Author-email: UNKNOWN
License: AGPL-3
Platform: UNKNOWN
Requires-Dist: odoo (<10.1dev,>=10.0)
Classifier: Programming Language :: Python :: 2.7
Classifier: Framework :: Odoo
Classifier: License :: OSI Approved :: GNU Affero General Public License v3
